transonic-0.8.0.dist-info/METADATA
transonic-0.8.0.dist-info/WHEEL
transonic-0.8.0.dist-info/entry_points.txt
transonic-0.8.0.dist-info/licenses/LICENSE.txt
transonic/__init__.py
transonic/_version.py
transonic/aheadoftime.py
transonic/analyses/__init__.py
transonic/analyses/beniget.py
transonic/analyses/blocks_if.py
transonic/analyses/capturex.py
transonic/analyses/extast.py
transonic/analyses/justintime.py
transonic/analyses/objects_from_str.py
transonic/analyses/parser.py
transonic/analyses/util.py
transonic/backends/__init__.py
transonic/backends/base.py
transonic/backends/base_jit.py
transonic/backends/cython.py
transonic/backends/for_classes.py
transonic/backends/for_test_set_backend.py
transonic/backends/jax.py
transonic/backends/numba.py
transonic/backends/py.py
transonic/backends/pythran.py
transonic/backends/typing.py
transonic/compiler.py
transonic/config.py
transonic/dist.py
transonic/justintime.py
transonic/log.py
transonic/mpi.py
transonic/progress.py
transonic/run.py
transonic/signatures.py
transonic/testing.py
transonic/typing.py
transonic/util.py
transonic_cl/__init__.py
transonic_cl/clean_dir.py
transonic_cl/cython.py
transonic_cl/cythonize.py
transonic_cl/get_includes.py
transonic_cl/init_meson.py
transonic_cl/run_backend.py
transonic-0.8.0.dist-info/RECORD
