Metadata-Version: 2.4
Name: transonic
Version: 0.8.0
Summary: Make your Python code fly at transonic speeds!
Keywords: pythran
Author-Email: Pierre Augier <pierre.augier@univ-grenoble-alpes.fr>
License-Expression: BSD-3-Clause
License-File: LICENSE.txt
Classifier: Programming Language :: Python :: 3
Classifier: Programming Language :: Python :: 3.11
Classifier: Programming Language :: Python :: 3.12
Classifier: Programming Language :: Python :: 3.13
Classifier: Programming Language :: Python :: 3.14
Project-URL: Source, https://foss.heptapod.net/fluiddyn/transonic
Project-URL: Documentation, https://transonic.readthedocs.io
Project-URL: Git Mirror, https://github.com/fluiddyn/transonic
Requires-Python: >=3.11
Requires-Dist: autopep8
Requires-Dist: beniget~=0.4.2
Requires-Dist: gast~=0.6.0
Requires-Dist: numpy
Provides-Extra: mpi
Requires-Dist: mpi4py; extra == "mpi"
